{
  "gitSyncId": "6811d55e4101ca4f4d2f6d2e_1c59e93a-5542-4e5d-a142-2069ffff94c8",
  "id": "Quản lý báo cáo_JSEcharts_dq_6thang_3.fetchData",
  "pluginId": "js-plugin",
  "pluginType": "JS",
  "unpublishedAction": {
    "actionConfiguration": {
      "encodeParamsToggle": true,
      "jsArguments": [],
      "paginationType": "NONE",
      "timeoutInMillisecond": 10000
    },
    "collectionId": "Quản lý báo cáo_JSEcharts_dq_6thang_3",
    "confirmBeforeExecute": false,
    "datasource": {
      "isAutoGenerated": false,
      "name": "UNUSED_DATASOURCE",
      "pluginId": "js-plugin"
    },
    "dynamicBindingPathList": [
      {
        "key": "body"
      }
    ],
    "executeOnLoad": true,
    "fullyQualifiedName": "JSEcharts_dq_6thang_3.fetchData",
    "name": "fetchData",
    "pageId": "Quản lý báo cáo",
    "userSetOnLoad": false
  }
}