{
  "gitSyncId": "6811d55e4101ca4f4d2f6d2e_d5939d39-4de1-4c6c-8327-346bcf26a2d5",
  "id": "Quản lý báo cáo_Counttaikhoandntc_3",
  "pluginId": "postgres-plugin",
  "pluginType": "DB",
  "unpublishedAction": {
    "actionConfiguration": {
      "body": "SELECT \n    mt.TenMucTieu,\n    COUNT(tk.ID) AS SoLuongTaiKhoanThamNhapDuoc\nFROM \n    TaiKhoan tk\nJOIN \n    Domain d ON tk.DomainID = d.ID\nJOIN \n    MucTieu mt ON d.MucTieuID = mt.ID\nWHERE \n    tk.TrangThai = 'Đăng nhập thành công'\nGROUP BY \n    mt.TenMucTieu\nORDER BY \n    SoLuongTaiKhoanThamNhapDuoc DESC;\n",
      "encodeParamsToggle": true,
      "paginationType": "NONE",
      "pluginSpecifiedTemplates": [
        {
          "value": true
        }
      ],
      "timeoutInMillisecond": 10000
    },
    "confirmBeforeExecute": false,
    "datasource": {
      "id": "csdltc",
      "isAutoGenerated": false,
      "name": "csdltc",
      "pluginId": "postgres-plugin"
    },
    "dynamicBindingPathList": [],
    "executeOnLoad": true,
    "name": "Counttaikhoandntc_3",
    "pageId": "Quản lý báo cáo",
    "userSetOnLoad": false
  }
}