{
  "gitSyncId": "6811d55e4101ca4f4d2f6d2e_f55723ae-9190-4f16-9736-6e495107ed57",
  "id": "Public.muctieu_Query1",
  "pluginId": "postgres-plugin",
  "pluginType": "DB",
  "unpublishedAction": {
    "actionConfiguration": {
      "body": "SELECT ID, TenMucTieu, MucTieuID FROM public.\"muctieu\";",
      "encodeParamsToggle": true,
      "paginationType": "NONE",
      "pluginSpecifiedTemplates": [
        {
          "value": false
        }
      ],
      "timeoutInMillisecond": 10000
    },
    "confirmBeforeExecute": false,
    "datasource": {
      "id": "csdltc",
      "isAutoGenerated": false,
      "name": "csdltc",
      "pluginId": "postgres-plugin"
    },
    "dynamicBindingPathList": [],
    "executeOnLoad": true,
    "name": "Query1",
    "pageId": "Public.muctieu",
    "userSetOnLoad": true
  }
}