{
  "gitSyncId": "6811d55e4101ca4f4d2f6d2e_8f40ca18-5800-494b-9ee9-9fcfa601382f",
  "id": "Quản lý các dữ liệu khác_JS_taikhoantm_1.fetchData",
  "pluginId": "js-plugin",
  "pluginType": "JS",
  "unpublishedAction": {
    "actionConfiguration": {
      "encodeParamsToggle": true,
      "jsArguments": [],
      "paginationType": "NONE",
      "timeoutInMillisecond": 10000
    },
    "collectionId": "Quản lý các dữ liệu khác_JS_taikhoantm_1",
    "confirmBeforeExecute": false,
    "datasource": {
      "isAutoGenerated": false,
      "name": "UNUSED_DATASOURCE",
      "pluginId": "js-plugin"
    },
    "dynamicBindingPathList": [
      {
        "key": "body"
      }
    ],
    "executeOnLoad": true,
    "fullyQualifiedName": "JS_taikhoantm_1.fetchData",
    "name": "fetchData",
    "pageId": "Quản lý các dữ liệu khác",
    "userSetOnLoad": false
  }
}