{
  "gitSyncId": "6811d55e4101ca4f4d2f6d2e_175e3958-f2ae-4b84-9ded-3a2b89080cb4",
  "id": "ChiTietKeHoach_KeHoach",
  "pluginId": "postgres-plugin",
  "pluginType": "DB",
  "unpublishedAction": {
    "actionConfiguration": {
      "body": "SELECT * FROM public.kehoach WHERE id = {{appsmith.store.selectedKeHoachId}};",
      "encodeParamsToggle": true,
      "paginationType": "NONE",
      "pluginSpecifiedTemplates": [
        {
          "value": false
        }
      ],
      "timeoutInMillisecond": 10000
    },
    "confirmBeforeExecute": false,
    "datasource": {
      "id": "csdltc",
      "isAutoGenerated": false,
      "name": "csdltc",
      "pluginId": "postgres-plugin"
    },
    "dynamicBindingPathList": [
      {
        "key": "body"
      }
    ],
    "executeOnLoad": true,
    "name": "KeHoach",
    "pageId": "ChiTietKeHoach",
    "userSetOnLoad": false
  }
}